pformat/__init__.py
pformat/format_options.py
pformat/indentation_utility.py
pformat/named_types.py
pformat/pretty_formatter.py
pformat/text_style.py
pformat/type_formatter.py
pformat/type_projection.py
pformat/type_specific_callable.py
pformat/typing_utility.py
pypformat-1.2.4.dist-info/licenses/LICENSE
pypformat-1.2.4.dist-info/METADATA
pypformat-1.2.4.dist-info/WHEEL
pypformat-1.2.4.dist-info/top_level.txt
pypformat-1.2.4.dist-info/RECORD
