Metadata-Version: 2.4
Name: pypformat
Version: 1.2.4
Summary: Python pretty formatting package
Author: SpectraL519
License-Expression: MIT
Project-URL: Repository, https://github.com/SpectraL519/pypformat.git
Keywords: string,format,formatting,pretty,print
Classifier: Development Status :: 5 - Production/Stable
Classifier: Intended Audience :: Developers
Classifier: Topic :: Software Development :: Libraries :: Python Modules
Classifier: Programming Language :: Python :: 3
Classifier: Programming Language :: Python :: 3.9
Classifier: Programming Language :: Python :: 3.10
Classifier: Programming Language :: Python :: 3.11
Classifier: Programming Language :: Python :: 3.12
Classifier: Programming Language :: Python :: 3.13
Requires-Python: >=3.9
License-File: LICENSE
Requires-Dist: colored==2.2.*
Provides-Extra: dev
Requires-Dist: pytest; extra == "dev"
Requires-Dist: tox; extra == "dev"
Requires-Dist: ruff; extra == "dev"
Requires-Dist: icecream; extra == "dev"
Dynamic: license-file
